odoo8_addon_survey_partner_tag_share-8.0.1.0.0.99.dev9-nspkg.pth
odoo_addons/survey_partner_tag_share/README.rst
odoo_addons/survey_partner_tag_share/__init__.py
odoo_addons/survey_partner_tag_share/__openerp__.py
odoo_addons/survey_partner_tag_share/i18n/fr.po
odoo_addons/survey_partner_tag_share/i18n/hr.po
odoo_addons/survey_partner_tag_share/i18n/sl.po
odoo_addons/survey_partner_tag_share/i18n/survey_partner_tag_share.pot
odoo_addons/survey_partner_tag_share/static/description/icon.png
odoo_addons/survey_partner_tag_share/tests/__init__.py
odoo_addons/survey_partner_tag_share/tests/test_survey_email_compose_message.py
odoo_addons/survey_partner_tag_share/wizard/__init__.py
odoo_addons/survey_partner_tag_share/wizard/survey_email_compose_message.py
odoo_addons/survey_partner_tag_share/wizard/survey_email_compose_message.xml
odoo8_addon_survey_partner_tag_share-8.0.1.0.0.99.dev9.dist-info/METADATA
odoo8_addon_survey_partner_tag_share-8.0.1.0.0.99.dev9.dist-info/WHEEL
odoo8_addon_survey_partner_tag_share-8.0.1.0.0.99.dev9.dist-info/namespace_packages.txt
odoo8_addon_survey_partner_tag_share-8.0.1.0.0.99.dev9.dist-info/top_level.txt
odoo8_addon_survey_partner_tag_share-8.0.1.0.0.99.dev9.dist-info/RECORD
